{
  "schema_version": "open-source-learning-audit-v1",
  "knowledge_id": "open-source-learning-v1",
  "status": "operational_healthy",
  "knowledge_snapshot_fingerprint": "86b5d8da34601a7ff59e94029ccf43914d83b14f06764962425875cdbd85ecbc",
  "counts": {
    "fixed_source_snapshots": 6,
    "clean_room_pattern_cards": 12,
    "internal_lesson_cards": 9,
    "registry_lineage_edges": 29,
    "lifecycle_records": 29,
    "pending_source_update_proposals": 0,
    "pending_lesson_feedback_drafts": 0,
    "pending_license_reviews": 0,
    "pending_review_items": 0,
    "review_events": 17,
    "approved_for_manual_curation": 7,
    "rejected_lesson_feedback": 2,
    "rejected_source_updates": 1,
    "pending_lesson_promotion_candidates": 0,
    "promoted_lesson_candidates": 6
  },
  "sources": {
    "freqtrade-strategies": "dbd5b0b21cfbf5ee80588d37458ace2467b7f8a4",
    "jesse": "fa63531cae6c09b978711dc1892285067304e2df",
    "qlib": "d5379c520f66a39953bad76234a7019a72796fd0",
    "lean": "0269115d3cfbf691c7a0b7cfcc9ed412cafb91f6",
    "nautilus-trader": "3ffa0ca4bea7876a7f78f8799fd73426059a097a",
    "hummingbot": "816b8ab539360557cee7d9248c2f24473b10b16f"
  },
  "governance": {
    "public_repository_source_class": "C",
    "class_c_only_result": "reject",
    "proposal_requirement": "at_least_one_A_or_B",
    "source_update_requires_human_approval": true,
    "lesson_promotion_requires_human_approval": true,
    "candidate_creation_authorized": false,
    "backtest_authorized": false,
    "strategy_mutation_authorized": false
  },
  "integration": {
    "director_schema_version": 10,
    "registry_integrity": "ok",
    "protected_proposal_campaign_counts_unchanged": true,
    "discovery_context": "research/knowledge/open-source-v1/current-context.json",
    "current_state_snapshot": "research-state-16cb1973ce0390d7",
    "knowledge_broker": {
      "enabled": true,
      "consumer": "research_discovery_researcher",
      "ranking": "deterministic_weighted_lexical_v2",
      "max_patterns": 4,
      "max_lessons": 4,
      "packet_injection": "automatic",
      "usage_lineage": "idempotent_retrieved_for"
    },
    "learning_loop": {
      "idea_selection_binding": "required_for_broker_enabled_runs",
      "critic_verification": "required",
      "director_gate": "verified_binding_required",
      "worker_dispatch": "provider_neutral_lease_queue",
      "campaign_feedback_drafts": 9,
      "feedback_review_status": "7_approved_for_manual_curation_2_rejected",
      "lesson_curation_status": "6_promoted_0_rejected",
      "deduplication": "7_approved_feedback_to_6_candidates",
      "promotion_review_packet": "research/knowledge/curation/open-source-learning-v1-review-batch-20260719/promotion-review-packet.json",
      "promotion_review_packet_fingerprint": "63b2c18264c837e38c09133cbf997442d6571ccb9c6eb551ffc514b72425c795",
      "promotion_approval_fingerprint": "22a664f33bd89f4d780a0ec40a7d6d42e3d0d88f18aa642b2d0720668bc94b1e",
      "promotion_batch": "reports/audits/open-source-learning-v1/promotion-batches/open-source-learning-v1-lesson-promotion-20260720",
      "automatic_lesson_promotion_authorized": false
    },
    "maintenance": {
      "source_refresh_report": "reports/audits/open-source-learning-v1/source-refresh-report.json",
      "source_refresh_current": 5,
      "source_refresh_update_available": 1,
      "source_refresh_check_failed": 0,
      "license_reviews_required": 0,
      "automatic_source_update_authorized": false,
      "retrieval_evaluation_report": "reports/audits/open-source-learning-v1/retrieval-evaluation.json",
      "retrieval_cases": 8,
      "retrieval_hit_rate_at_4": 1.0,
      "retrieval_first_rank_rate": 1.0,
      "retrieval_status": "passed",
      "pending_review_packet": "reports/audits/open-source-learning-v1/pending-review-packet.json",
      "pending_review_items": 0,
      "current_recommendations": 0,
      "review_events": 17,
      "completed_review_batch": "reports/audits/open-source-learning-v1/review-batches/open-source-learning-v1-review-batch-20260719",
      "completed_review_batch_approvals": 8,
      "completed_review_batch_rejections": 3,
      "batch_approval_fingerprint": "68279cbb265bd1fd872e94249450d02c59732d928a81275bc29c96bfd68f568a",
      "health_report": "reports/audits/open-source-learning-v1/learning-loop-health.json",
      "health_status": "healthy",
      "health_warnings": [],
      "execution_authorized": false
    }
  },
  "verification": {
    "related_tests_passed": 108,
    "related_tests_failed": 0,
    "guard_harness_diff": "passed",
    "guard_no_secret_material": "passed",
    "guard_trading_surface": "passed",
    "selected_changed_surface_workflow_tests": "passed"
  },
  "execution_boundaries": {
    "candidates_created": 0,
    "backtests_run": 0,
    "validation_accesses": 0,
    "holdout_accesses": 0,
    "formal_strategy_modified": false,
    "formal_base_modified": false,
    "dry_run_or_live_operations": 0
  },
  "result": "The explicit human decision to approve six and reject zero lesson candidates was applied. Six candidates entered the formal Broker catalog, the temporal-retention card superseded the old ranging-short negative-contributor card, the formal lesson count is nine, retrieval evaluation passes 8/8, and no automatic promotion, trading, backtest, Validation/Holdout access, or strategy mutation was authorized."
}
